ghub/__init__.py
ghub/__main__.py
ghub/_version.py
ghub/cliutils.py
ghub/commands.py
ghub/context.py
ghub/ghubutils.py
ghub/githubutils.py
ghub/repoutils.py
ghub/runner.py
ghubunix-1.1.0.dist-info/LICENSE
ghubunix-1.1.0.dist-info/METADATA
ghubunix-1.1.0.dist-info/WHEEL
ghubunix-1.1.0.dist-info/entry_points.txt
ghubunix-1.1.0.dist-info/top_level.txt
ghubunix-1.1.0.dist-info/RECORD
